armada/__init__.py
armada/auth.py
armada/hooks.py
armada/links.py
armada/log_manager.py
armada/model.py
armada/plugin.py
armada/triggers.py
armada/utils.py
armada/operators/armada.py
armada/operators/errors.py
armada/policies/reattach.py
armada/policies/retry.py
armada_airflow-1.0.15.dist-info/licenses/LICENSE
armada_airflow-1.0.15.dist-info/METADATA
armada_airflow-1.0.15.dist-info/WHEEL
armada_airflow-1.0.15.dist-info/entry_points.txt
armada_airflow-1.0.15.dist-info/top_level.txt
armada_airflow-1.0.15.dist-info/RECORD
