Metadata-Version: 2.4
Name: armada_airflow
Version: 1.0.15
Summary: Armada Airflow Operator
Author-email: Armada-GROSS <armada@armadaproject.io>
License: Apache Software License
Project-URL: repository, https://github.com/armadaproject/armada
Classifier: Programming Language :: Python :: 3
Classifier: Operating System :: OS Independent
Requires-Python: >=3.10
License-File: LICENSE
Requires-Dist: armada-client>=0.4.8
Requires-Dist: apache-airflow>=2.6.3
Requires-Dist: types-protobuf==4.24.0.1
Requires-Dist: kubernetes>=23.6.0
Requires-Dist: kubernetes_asyncio>=24.2.3
Requires-Dist: opentelemetry-exporter-otlp>=1.28.1
Provides-Extra: format
Requires-Dist: black>=24.0.0; extra == "format"
Requires-Dist: flake8>=7.0.0; extra == "format"
Requires-Dist: pylint>=2.17.5; extra == "format"
Provides-Extra: test
Requires-Dist: pytest==7.3.1; extra == "test"
Requires-Dist: coverage==6.5.0; extra == "test"
Requires-Dist: pytest-asyncio==0.21.1; extra == "test"
Requires-Dist: pytest-mock>=3.14.0; extra == "test"
Provides-Extra: docs
Requires-Dist: sphinx==7.1.2; extra == "docs"
Requires-Dist: sphinx-jekyll-builder==0.3.0; extra == "docs"
Requires-Dist: sphinx-toolbox==3.2.0b1; extra == "docs"
Requires-Dist: sphinx-markdown-builder==0.5.5; extra == "docs"
Dynamic: license-file
